MANIFEST.in
README.md
requirements.txt
setup.cfg
setup.py
meos_sdk/__init__.py
meos_sdk/utils.py
meos_sdk.egg-info/PKG-INFO
meos_sdk.egg-info/SOURCES.txt
meos_sdk.egg-info/dependency_links.txt
meos_sdk.egg-info/entry_points.txt
meos_sdk.egg-info/requires.txt
meos_sdk.egg-info/top_level.txt
meos_sdk/app/__init__.py
meos_sdk/app/app.py
meos_sdk/app/client.py
meos_sdk/app/config.py
meos_sdk/app/exceptions.py
meos_sdk/app/response.py
meos_sdk/cli/__init__.py
meos_sdk/cli/cli.py
meos_sdk/cli/main.py
tests/app/__init__.py
tests/app/_mock_app.py
tests/app/conftest.py
tests/app/test_app.py